legiscrape/__init__.py
legiscrape/captions.py
legiscrape/cli.py
legiscrape/granicus-captions.schema.json
legiscrape/video.py
legiscrape-0.0.1.dist-info/DESCRIPTION.rst
legiscrape-0.0.1.dist-info/METADATA
legiscrape-0.0.1.dist-info/RECORD
legiscrape-0.0.1.dist-info/WHEEL
legiscrape-0.0.1.dist-info/entry_points.txt
legiscrape-0.0.1.dist-info/metadata.json
legiscrape-0.0.1.dist-info/top_level.txt
