Metadata-Version: 2.0
Name: legiscrape
Version: 0.0.1
Summary: Legistar Scraper
Home-page: http://github.com/notpeter/legiscrape
Author: Peter Tripp
Author-email: petertripp@gmail.com
License: MIT
Platform: UNKNOWN
Classifier: Development Status :: 3 - Alpha
Classifier: License :: OSI Approved :: MIT License
Classifier: Programming Language :: Python :: 3.5
Classifier: Environment :: Console
Requires-Dist: jsonschema
